CHANGELOG.rst
LICENSE.txt
MANIFEST.in
README.rst
TODO.txt
VERSION.txt
setup.cfg
setup.py
aadict/__init__.py
aadict/test.py
aadict.egg-info/PKG-INFO
aadict.egg-info/SOURCES.txt
aadict.egg-info/dependency_links.txt
aadict.egg-info/requires.txt
aadict.egg-info/top_level.txt
aadict.egg-info/zip-safe