Metadata-Version: 1.1
Name: aadict
Version: 0.2.1
Summary: An auto-attribute dict (and a couple of other useful dict functions)
Home-page: http://github.com/metagriffin/aadict
Author: metagriffin
Author-email: mg.pypi@uberdev.org
License: GPLv3+
Keywords: auto attribute access dict helpers pick omit
Platform: any
Classifier: Development Status :: 5 - Production/Stable
Classifier: Intended Audience :: Developers
Classifier: Programming Language :: Python
Classifier: Operating System :: OS Independent
Classifier: Natural Language :: English
Classifier: License :: OSI Approved :: GNU General Public License v3 or later (GPLv3+)
